ml_builder/__init__.py
ml_builder/utils/__init__.py
ml_builder/utils/import_utils.py
ml_builder-0.1.0.data/data/share/info/README.md
ml_builder-0.1.0.dist-info/METADATA
ml_builder-0.1.0.dist-info/WHEEL
ml_builder-0.1.0.dist-info/top_level.txt
ml_builder-0.1.0.dist-info/RECORD
